{"azurirano":"20. 6. 2026. u 12:32","globalna_napomena":"Zbog EES registracije putnika moguća su duža zadržavanja na svim prelazima prema Hrvatskoj.","prelazi":{"gradina":{"ulaz":"zuto","izlaz":"zeleno","info":"Pojačan promet na ulazu u BiH."},"brod":{"ulaz":"zuto","izlaz":"zuto","info":"Pojačan promet u oba smjera."},"samac":{"ulaz":"zeleno","izlaz":"zeleno","info":"Zadržavanja do 30 min."},"orasje":{"ulaz":"zeleno","izlaz":"zeleno","info":"Zadržavanja do 30 min."},"brcko":{"ulaz":"zeleno","izlaz":"zeleno","info":"Zadržavanja do 30 min. Otvoren za vozila do 3,5 tone."},"raca":{"ulaz":"zeleno","izlaz":"zeleno","info":"Zadržavanja do 30 min."},"sepak":{"ulaz":"zeleno","izlaz":"zeleno","info":"Zadržavanja do 30 min. Zabranjen saobraćaj za teretna vozila."},"karakaj":{"ulaz":"zeleno","izlaz":"zeleno","info":"Zadržavanja do 30 min. Otvoren za sve kategorije vozila."},"bratunac":{"ulaz":"zeleno","izlaz":"zeleno","info":"Zadržavanja do 30 min."},"skelani":{"ulaz":"zeleno","izlaz":"zeleno","info":"Zadržavanja do 30 min."},"vardiste":{"ulaz":"zeleno","izlaz":"zeleno","info":"Zadržavanja do 30 min."},"metaljka":{"ulaz":"zeleno","izlaz":"zeleno","info":"Zadržavanja do 30 min."},"hum":{"ulaz":"zeleno","izlaz":"zeleno","info":"Zadržavanja do 30 min."},"deleusa":{"ulaz":"zeleno","izlaz":"zuto","info":"Pojačan promet na izlazu."},"klobuk":{"ulaz":"zeleno","izlaz":"zeleno","info":"Zadržavanja do 30 min."},"zupci":{"ulaz":"zeleno","izlaz":"zuto","info":"Pojačan promet na izlazu."},"ivanica":{"ulaz":"zeleno","izlaz":"zeleno","info":"Zadržavanja do 30 min."},"neum-2":{"ulaz":"zeleno","izlaz":"zeleno","info":"Zadržavanja do 30 min."},"neum-1":{"ulaz":"zeleno","izlaz":"zuto","info":"Pojačan promet na izlazu."},"doljani":{"ulaz":"zeleno","izlaz":"zuto","info":"Pojačan promet na izlazu."},"bijaca":{"ulaz":"zeleno","izlaz":"zuto","info":"Pojačan promet na izlazu."},"crveni-grm":{"ulaz":"zeleno","izlaz":"zuto","info":"Pojačan promet na izlazu."},"gorica":{"ulaz":"zeleno","izlaz":"zuto","info":"Pojačan promet na izlazu."},"kamensko":{"ulaz":"zeleno","izlaz":"zuto","info":"Pojačan promet na izlazu."},"izacic":{"ulaz":"zeleno","izlaz":"zuto","info":"Pojačan promet na izlazu."},"svilaj":{"ulaz":"zeleno","izlaz":"zeleno","info":"Zadržavanja do 30 min."},"bosanska-gradiska":{"ulaz":"zeleno","izlaz":"zeleno","info":"Zadržavanja do 30 min."},"velika-kladusa":{"ulaz":"zeleno","izlaz":"zuto","info":"Pojačan promet na izlazu."},"bosanska-kostajnica":{"ulaz":"zuto","izlaz":"zeleno","info":"Pojačan promet na ulazu u Bosnu i Hercegovinu. Zadržavanja na izlazu do 30 min."},"bosanska-dubica":{"ulaz":"zeleno","izlaz":"zeleno","info":"Zadržavanja do 30 min."}}}